{
  "slug": "fundedelite",
  "ファーム名": "FundedElite",
  "拠点国": "イタリア",
  "創業年": "2023年",
  "公式URL": "https://app.fundedelite.jp",
  "カテゴリ": "FX",
  "日本対応": "日本語HP",
  "ファームピッチ": "高いカスタマイズ性（レバレッジ、損失限界、目標、利益分配）、無料リトライオプション、低コストのフラッシュアクティベーションなどを提供",
  "リワードプログラム": "",
  "スケールアップ": "Funded口座での出金3回ごとに残高が10%増加し、最大ドローダウン枠が1%増加（最大14%まで）。出金5回で利益分配率が90%に拡大し、出金7回で週次出金へ移行。",
  "ブローカー": "提携パートナーブローカー（Purple Trading等）",
  "プラットフォーム": "MetaTrader 5 (MT5)、TradeLocker、Match Trader、cTrader",
  "Server Time": "EET/EEST (UTC+2 / UTC+3, 日本時間-7時間 / 日本時間-8時間)",
  "DD Reset": "00:00 Server Time (日本時間 07:00 / 08:00)",
  "レバレッジ": "## レバレッジ（F14）\n資産クラス別・フェーズ別のレバレッジ一覧。\n\n| 資産クラス | Challenge | Funded |\n| --- | --- | --- |\n| FX | 1:30, 1:50, 1:100 | 1:100 |\n| Equity Indices | 1:10 | 1:100 |\n| Precious Metals | 1:10 | 1:100 |\n| Energy & Gas | 1:10 | 1:10 |\n| Cryptocurrencies | 1:2 | 1:2 |\n\n※ FXペアのChallengeフェーズにおけるレバレッジは、チェックアウト時に1:30、1:50、1:100の中からカスタマイズ選択可能です。その他の資産クラスは固定となります。",
  "手数料": "## 手数料（F15）\n資産クラス別の取引手数料一覧。往復/片道の仕様と通貨単位を明記。\n\n| 資産クラス | 手数料 |\n| --- | --- |\n| FX | $3.00/lot（往復） |\n| Equity Indices (Spot) | $0.00/lot（往復） |\n| Gold, Silver, Crude Oil | $3.00/lot（往復） |\n| Platinum, Palladium, Natural Gas | $0.00/lot（往復） |\n| Cryptocurrencies | $0.00/lot（往復） |\n| Bonds & Volatility Derivatives | $0.00/lot（往復） |",
  "入金方法": "クレジットカード、銀行送金、暗号通貨、Google Pay、Apple Pay",
  "出金方法": "銀行送金、暗号通貨、Rise、PayPal",
  "出金ポリシー": "初回出金はFunded開始から21日後に可能。以降はデフォルトで隔週（購入時のカスタマイズで3〜21日の間隔を選択可能）。利益上限はなし。",
  "Profit Split": "60%、70%、80%、95%（購入時に選択可能）",
  "※Profit Split": "セカンドチャンス口座では50%に永久減額。インスタントチャレンジの初回出金は70%。スケールアップ後（5回出金後）は90%に拡大。ソフトブリーチ違反時は対象サイクルの分配率が30%に一時減額される。",
  "プラン名リスト": "2ステップ + 無料リトライ, 1ステップ + 無料リトライ, LITE 2ステップ, LITE 1ステップ, インスタント, フラッシュ・アクティベーション",
  "プラン比較テーブル": "| 項目 | 2ステップ + 無料リトライ | 1ステップ + 無料リトライ | LITE 2ステップ | LITE 1ステップ | インスタント | フラッシュ・アクティベーション |\n| --- | --- | --- | --- | --- | --- | --- |\n| ステップ | 2 | 1 | 2 | 1 | 0 | 1 |\n| 利益目標 | Challenge 1次: 6%〜12%<br>Challenge 2次: 5% | Challenge: 6%〜12% | Challenge 1次: 6%〜12%<br>Challenge 2次: 5% | Challenge: 8%〜12% | ー | Challenge: 6% |\n| 日次損失 | 5% | 3% | 4% | 3% | 3% | 3% |\n| 最大損失 | 5%〜10% | 5%〜10% | 6%〜10% | 5%〜10% | 6% | 6% |\n| 利益分配率 | 60%〜95% | 60%〜95% | 60%〜95% | 60%〜95% | 70%〜95% | 80% |\n| 出金頻度 | 隔週 | 隔週 | 隔週 | 隔週 | 隔週 | 隔週 |\n| 最短合格 | 6日 | 3日 | 6日 | 3日 | 0日 | 1日 |\n| 最速出金 | 21日 | 21日 | 21日 | 21日 | 21日 | 14日 |\n| トータル日数 | 27日 | 24日 | 27日 | 24日 | 21日 | 15日 |\n\n※ 出金頻度は購入時にカスタマイズ可能（3日〜21日）ですが、フラッシュ・アクティベーションを除くプランでは一律で「初回出金は21日後」の特例が適用されるため、最速出金は21日で算出しています。フラッシュ・アクティベーションの出金頻度は14日ごとに設定されています。\n※ フラッシュ・アクティベーションは最低取引日数制限がありませんが、最短合格を1日として算出しています。",
  "メールアドレス": "",
  "アフィリエイトURL": "https://app.fundedelite.com?aff=AFF3027003",
  "クーポンコード": "",
  "プラン一覧": [
    "2ステップ + 無料リトライ",
    "1ステップ + 無料リトライ",
    "LITE 2ステップ",
    "LITE 1ステップ",
    "インスタント",
    "フラッシュ・アクティベーション"
  ],
  "攻略_DD": "<p>FundedEliteでは、プランによって日次損失・最大損失の設定が異なります。多くのプランで購入時のカスタマイズが可能で、フラッシュ・アクティベーションのみFundedフェーズでDD計算基準が変更される特殊な仕様となっています。</p><table header-row=\"true\" header-column=\"false\"><tr><td>プラン</td><td>フェーズ</td><td>日次損失上限</td><td>計算基準（日次）</td><td>最大損失上限</td><td>計算基準（最大）</td></tr><tr><td>2ステップ + 無料リトライ</td><td>Challenge</td><td>5%</td><td>Trailing（Higher B or E EOD）</td><td>5%〜10%</td><td>Static</td></tr><tr><td>2ステップ + 無料リトライ</td><td>Funded</td><td>5%</td><td>Trailing（Higher B or E EOD）</td><td>5%〜10%</td><td>Static</td></tr><tr><td>1ステップ + 無料リトライ</td><td>Challenge</td><td>3%</td><td>Trailing（Higher B or E EOD）</td><td>5%〜10%</td><td>Static</td></tr><tr><td>1ステップ + 無料リトライ</td><td>Funded</td><td>3%</td><td>Trailing（Higher B or E EOD）</td><td>5%〜10%</td><td>Static</td></tr><tr><td>LITE 2ステップ</td><td>Challenge</td><td>4%</td><td>Trailing（Higher B or E EOD）</td><td>6%〜10%</td><td>Static</td></tr><tr><td>LITE 2ステップ</td><td>Funded</td><td>4%</td><td>Trailing（Higher B or E EOD）</td><td>6%〜10%</td><td>Static</td></tr><tr><td>LITE 1ステップ</td><td>Challenge</td><td>3%</td><td>Trailing（Higher B or E EOD）</td><td>5%〜10%</td><td>Static</td></tr><tr><td>LITE 1ステップ</td><td>Funded</td><td>3%</td><td>Trailing（Higher B or E EOD）</td><td>5%〜10%</td><td>Static</td></tr><tr><td>インスタント</td><td>Funded</td><td>3%</td><td>Trailing（Equity HWM）</td><td>6%</td><td>Trailing（Equity HWM）</td></tr><tr><td>フラッシュ・アクティベーション</td><td>Challenge</td><td>3%</td><td>Trailing（Higher B or E EOD）</td><td>6%</td><td>Static</td></tr><tr><td>フラッシュ・アクティベーション</td><td>Funded</td><td>3%</td><td>Trailing（Higher B or E EOD）</td><td>6%</td><td>Trailing（Equity HWM）</td></tr></table><p>DD計算のリセット時刻は00:00 Server Time（日本時間7:00/8:00）です。Trailing（Higher B or E EOD）では前営業日終値ベースの純資産額または残高の高い方を基準とします。Static計算では初期残高を基準とし、残高が増加しても損失下限は変動しません。Trailing（Equity HWM）では到達した最高有効証拠金を基準として計算されます。</p><p>合格に向けては、プランごとに異なるDD設定を把握し、特にTrailing（Higher B or E EOD）では前日終値ベースの計算であることを理解して資金管理を行う必要があります。</p><p>出金に向けては、フラッシュ・アクティベーションのFundedフェーズではDD計算基準がTrailing（Equity HWM）に変更されるため、運用中の最高到達有効証拠金を常に意識した取引が求められます。</p><p>セカンドチャンス口座では日次損失が3%に引き下げられる特殊ルールがあります。</p>",
  "攻略_取引ルール": "<p>FundedEliteでは、プランによってConsistency Ruleの適用状況や取引制限に違いがあります。</p><table header-row=\"true\" header-column=\"false\"><tr><td>プラン</td><td>Challenge</td><td>Funded</td><td>備考</td></tr><tr><td>2ステップ + 無料リトライ</td><td>※有（30万ドル口座のみ60%）</td><td>※有（30万ドル口座のみ60%）</td><td>標準口座では適用なし</td></tr><tr><td>1ステップ + 無料リトライ</td><td>※有（30万ドル口座のみ60%）</td><td>※有（30万ドル口座のみ60%）</td><td>標準口座では適用なし</td></tr><tr><td>LITE 2ステップ</td><td>※有（30万ドル口座のみ60%）</td><td>※有（30万ドル口座のみ60%）</td><td>標準口座では適用なし</td></tr><tr><td>LITE 1ステップ</td><td>記載なし</td><td>記載なし</td><td>ー</td></tr><tr><td>インスタント</td><td>ー</td><td>有（購入時アドオン選択可）</td><td>公式Q&Aに記載なし</td></tr><tr><td>フラッシュ・アクティベーション</td><td>なし</td><td>30%</td><td>1日の獲得利益が全期間の総利益の30%まで</td></tr></table><p>以下のテーブルは各プランのChallenge/Funded間の主要な差分を示します。具体的な数値やルールの詳細は各プランページの早見表・詳細セクションを参照してください。</p><table header-row=\"true\" header-column=\"false\"><tr><td>プラン</td><td>項目</td><td>Challenge</td><td>Funded</td></tr><tr><td>フラッシュ・アクティベーション</td><td>最大損失計算基準</td><td>Static</td><td>Trailing（Equity HWM）</td></tr><tr><td>フラッシュ・アクティベーション</td><td>一貫性ルール</td><td>なし</td><td>30%</td></tr><tr><td>フラッシュ・アクティベーション</td><td>最低取引日数</td><td>なし</td><td>3日</td></tr><tr><td>全プラン（インスタント除く）</td><td>リスクルール</td><td>なし</td><td>戦略リスク制限（50%）</td></tr></table><p>全プラン共通の取引制限として、最低3分間のポジション保持（スキャルピング制約）、週末トレードの禁止（アドオン購入時は除く）、手動戦略補助用EAのみ使用可能（完全自動売買禁止）、自身所有口座間のみコピートレード可能という条件があります。</p><table header-row=\"true\" header-column=\"false\"><tr><td>項目</td><td>プラン別の違い</td></tr><tr><td>最低取引日数</td><td>3日（LITE系・インスタント・フラッシュ）/ 5日（通常系）</td></tr><tr><td>利益条件</td><td>口座サイズの0.5%〜1%（プランにより異なる）</td></tr></table><p>禁止行為の具体的な行為名は各プランページの「禁止行為」項目を参照。</p><p>合格に向けては、プランごとに異なる最低取引日数と利益条件を満たし、Fundedフェーズで適用される戦略リスク制限（単一銘柄で日次損失上限の50%超禁止）を理解することです。</p><p>出金に向けては、一貫性ルールの適用状況とFundedフェーズでの戦略リスク制限を遵守し、特にフラッシュ・アクティベーションでは30%の一貫性制限が新たに追加されることに留意する必要があります。</p>",
  "攻略_出金": "<p>FundedEliteでは全プランで初回出金が21日後（フラッシュ・アクティベーション除く）、以降は隔週での出金が基本となります。フラッシュ・アクティベーションは最速15日での出金が可能です。</p><table header-row=\"true\" header-column=\"false\"><tr><td>プラン</td><td>頻度</td><td>最低取引日数（出金）</td><td>一貫性ルール</td><td>最低利益</td><td>利益分配</td><td>備考</td></tr><tr><td>2ステップ + 無料リトライ</td><td>隔週</td><td>5日</td><td>※有（30万ドル口座のみ60%）</td><td>なし</td><td>60%〜95%</td><td>初回21日後</td></tr><tr><td>1ステップ + 無料リトライ</td><td>隔週</td><td>5日</td><td>※有（30万ドル口座のみ60%）</td><td>なし</td><td>60%〜95%</td><td>初回21日後</td></tr><tr><td>LITE 2ステップ</td><td>隔週</td><td>3日</td><td>※有（30万ドル口座のみ60%）</td><td>なし</td><td>60%〜95%</td><td>初回21日後</td></tr><tr><td>LITE 1ステップ</td><td>隔週</td><td>3日</td><td>記載なし</td><td>なし</td><td>60%〜95%</td><td>初回21日後</td></tr><tr><td>インスタント</td><td>隔週</td><td>3日</td><td>有（アドオン選択可）</td><td>なし</td><td>70%〜95%</td><td>初回21日後</td></tr><tr><td>フラッシュ・アクティベーション</td><td>隔週</td><td>3日</td><td>30%</td><td>なし</td><td>80%</td><td>14日ごと</td></tr></table><table header-row=\"true\" header-column=\"false\"><tr><td>プラン</td><td>Steps</td><td>最短合格</td><td>最速出金</td><td>トータル日数</td><td>着金目安</td><td>備考</td></tr><tr><td>2ステップ + 無料リトライ</td><td>2</td><td>10日</td><td>21日</td><td>31日</td><td>記載なし</td><td>ー</td></tr><tr><td>1ステップ + 無料リトライ</td><td>1</td><td>5日</td><td>21日</td><td>26日</td><td>記載なし</td><td>ー</td></tr><tr><td>LITE 2ステップ</td><td>2</td><td>6日</td><td>21日</td><td>27日</td><td>記載なし</td><td>ー</td></tr><tr><td>LITE 1ステップ</td><td>1</td><td>3日</td><td>21日</td><td>24日</td><td>記載なし</td><td>ー</td></tr><tr><td>インスタント</td><td>0</td><td>0日</td><td>21日</td><td>21日</td><td>記載なし</td><td>ー</td></tr><tr><td>フラッシュ・アクティベーション</td><td>1</td><td>1日</td><td>14日</td><td>15日</td><td>記載なし</td><td>ー</td></tr></table><p>出金頻度は購入時に3〜21日の範囲でカスタマイズ可能ですが、フラッシュ・アクティベーションを除く全プランで初回出金は21日後の特例が適用されます。利益分配率は購入時に選択可能で、スケールアップにより出金5回後に90%まで拡大します。</p>",
  "価格テーブル": {
    "rows": [
      {
        "size": "¥1,000,000",
        "prices": {
          "1": "—",
          "p558": "—",
          "lite-2": "¥5,980",
          "lite-1": "¥7,800",
          "p562": "—",
          "p563": "—"
        }
      },
      {
        "size": "¥1,300,000",
        "prices": {
          "1": "¥22,800",
          "p558": "¥21,800",
          "lite-2": "—",
          "lite-1": "—",
          "p562": "¥32,800",
          "p563": "—"
        }
      },
      {
        "size": "¥2,000,000",
        "prices": {
          "1": "—",
          "p558": "—",
          "lite-2": "¥11,800",
          "lite-1": "¥15,800",
          "p562": "—",
          "p563": "—"
        }
      },
      {
        "size": "¥2,500,000",
        "prices": {
          "1": "¥32,800",
          "p558": "¥31,800",
          "lite-2": "¥17,800",
          "lite-1": "¥19,800",
          "p562": "¥69,800",
          "p563": "—"
        }
      },
      {
        "size": "¥5,000,000",
        "prices": {
          "1": "¥54,800",
          "p558": "¥52,800",
          "lite-2": "¥27,800",
          "lite-1": "¥31,800",
          "p562": "¥89,800",
          "p563": "¥700（合格後¥32,800）"
        }
      },
      {
        "size": "¥10,000,000",
        "prices": {
          "1": "¥84,800",
          "p558": "¥79,800",
          "lite-2": "¥59,800",
          "lite-1": "¥64,800",
          "p562": "¥178,000",
          "p563": "¥700（合格後¥69,800）"
        }
      },
      {
        "size": "¥20,000,000",
        "prices": {
          "1": "¥148,800",
          "p558": "¥134,800",
          "lite-2": "¥89,800",
          "lite-1": "¥108,000",
          "p562": "¥338,000",
          "p563": "¥700（合格後¥108,000）"
        }
      },
      {
        "size": "¥35,000,000",
        "prices": {
          "1": "¥298,000",
          "p558": "¥268,000",
          "lite-2": "¥188,000",
          "lite-1": "¥228,000",
          "p562": "—",
          "p563": "¥700（合格後¥228,000）"
        }
      },
      {
        "size": "¥50,000,000",
        "prices": {
          "1": "¥438,000",
          "p558": "¥398,000",
          "lite-2": "¥288,000",
          "lite-1": "¥348,000",
          "p562": "—",
          "p563": "—"
        }
      }
    ],
    "planCols": [
      "2ステップ + 無料リトライ",
      "1ステップ + 無料リトライ",
      "LITE 2ステップ",
      "LITE 1ステップ",
      "インスタント",
      "フラッシュ・アクティベーション"
    ]
  }
}
